[
    {
        "id": 1,
        "employees": 852,
        "completed": 403,
        "pending": 311,
        "expiring": 24,
        "expired": 114,
        "name": "Dynamic Reports",
        "location": "Perth, Austrailia",
        "startDate": "01/01/2001",
        "endDate": "03/03/2003"
    },
    {
        "id": 7,
        "employees": 300,
        "completed": 0,
        "pending": 3,
        "expiring": 23,
        "expired": 67,
        "name": "Ninja Dojo",
        "location": "Kyoto, Japan",
        "startDate": "05/21/2011",
        "endDate": "07/07/2012"
    },
    {
        "id": 10,
        "employees": 5,
        "completed": 5,
        "pending": 0,
        "expiring": 0,
        "expired": 0,
        "name": "Volcano Base",
        "location": "Irvine, California",
        "startDate": "10/31/2014",
        "endDate": "09/10/2015"
    },
    {
        "id": 4,
        "employees": 1000,
        "completed": 999,
        "pending": 0,
        "expiring": 0,
        "expired": 1,
        "name": "Massive Dynamic",
        "location": "Sioux City, Iowa",
        "startDate": "02/23/2013",
        "endDate": "06/15/2014"
    },
    {
        "id": 9,
        "employees": 53,
        "completed": 40,
        "pending": 3,
        "expiring": 5,
        "expired": 5,
        "name": "Daily Planet",
        "location": "Metropolis, New York",
        "startDate": "03/12/2002",
        "endDate": "05/30/2004"
    }
]